{
  "id": "DIS-E009",
  "title": "LogicalDisplay getDisplayInfoLocked() 快取條件判斷反轉",
  "domain": "display",
  "difficulty": "easy",
  "cts_test": "android.display.cts.DisplayTest#testGetDisplayAttrs",
  "cts_module": "CtsDisplayTestCases",
  "injection_point": "DIS-019",
  "injection_type": ["STATE", "COND"],
  "affected_files": ["frameworks/base/services/core/java/com/android/server/display/LogicalDisplay.java"],
  "tags": ["condition-inversion", "null-check", "lazy-initialization", "cache", "npe"],
  "estimated_time_minutes": 15,
  "bug_description": "將快取初始化條件 '== null' 誤寫成 '!= null'，導致首次呼叫返回 null 觸發 NPE",
  "root_cause": "條件判斷反轉，破壞 lazy initialization 模式",
  "fix_complexity": "single-line"
}
